odoo/addons/sm_partago_user/__init__.py
odoo/addons/sm_partago_user/__manifest__.py
odoo/addons/sm_partago_user/controllers/__init__.py
odoo/addons/sm_partago_user/controllers/controllers.py
odoo/addons/sm_partago_user/email_tmpl/cs_access_requested.xml
odoo/addons/sm_partago_user/email_tmpl/cs_company_access_requested.xml
odoo/addons/sm_partago_user/email_tmpl/cs_complete_data_soci_not_found_email.xml
odoo/addons/sm_partago_user/email_tmpl/cs_complete_data_successful_email.xml
odoo/addons/sm_partago_user/email_tmpl/cs_email_already_active.xml
odoo/addons/sm_partago_user/email_tmpl/cs_missing_data_email.xml
odoo/addons/sm_partago_user/models/__init__.py
odoo/addons/sm_partago_user/models/models_carsharing_update_data.py
odoo/addons/sm_partago_user/models/models_carsharing_update_data_fetch_wizard.py
odoo/addons/sm_partago_user/models/models_sm_company.py
odoo/addons/sm_partago_user/models/models_sm_member.py
odoo/addons/sm_partago_user/models/models_sm_member_csgroup.py
odoo/addons/sm_partago_user/models/models_sm_res_config_settings.py
odoo/addons/sm_partago_user/models/models_smp_carsharing_registration_request.py
odoo/addons/sm_partago_user/models/models_smp_carsharing_registration_wizard.py
odoo/addons/sm_partago_user/models/models_smp_user_cron.py
odoo/addons/sm_partago_user/models/models_smp_user_utils.py
odoo/addons/sm_partago_user/security/ir.model.access.csv
odoo/addons/sm_partago_user/services/__init__.py
odoo/addons/sm_partago_user/services/partner_services.py
odoo/addons/sm_partago_user/views/views.xml
odoo/addons/sm_partago_user/views/views_carsharing_update_data.xml
odoo/addons/sm_partago_user/views/views_carsharing_update_data_fetch_wizard.xml
odoo/addons/sm_partago_user/views/views_cron.xml
odoo/addons/sm_partago_user/views/views_cs_registration_request.xml
odoo/addons/sm_partago_user/views/views_cs_registration_wizard.xml
odoo/addons/sm_partago_user/views/views_db.xml
odoo/addons/sm_partago_user/views/views_member_cs_groups.xml
odoo11_addon_sm_partago_user-11.0.0.0.1.dist-info/METADATA
odoo11_addon_sm_partago_user-11.0.0.0.1.dist-info/WHEEL
odoo11_addon_sm_partago_user-11.0.0.0.1.dist-info/top_level.txt
odoo11_addon_sm_partago_user-11.0.0.0.1.dist-info/RECORD
